gitlab_sdk/__init__.py
gitlab_sdk/_version.py
gitlab_sdk/client.py
tests/__init__.py
tests/test_client.py
gitlab_sdk-0.2.6.dist-info/METADATA
gitlab_sdk-0.2.6.dist-info/WHEEL
gitlab_sdk-0.2.6.dist-info/top_level.txt
gitlab_sdk-0.2.6.dist-info/RECORD
