Metadata-Version: 2.1
Name: gitlab-sdk
Version: 0.2.6
Summary: Client side Python SDK for GitLab Application services
Home-page: https://gitlab.com/gitlab-org/analytics-section/product-analytics/gl-application-sdk-python
Author: GitLab
Author-email: gitlab_rubygems@gitlab.com
License: UNKNOWN
Platform: UNKNOWN
Requires-Python: >3.5
Requires-Dist: snowplow-tracker >=1.0.0
